blobulator/__init__.py
blobulator/__main__.py
blobulator/amino_acids.py
blobulator/compute_blobs.py
blobulator/compute_snps.py
blobulator/generate_colormaps.py
blobulator/data/Table_S1.csv
blobulator/data/blobulated.csv
blobulator/data/disorderCMap.csv
blobulator/data/enrichCMap.csv
blobulator/data/enrichCMap_p.csv
blobulator/data/enrichCMap_s.csv
blobulator/data/enrichment.csv
blobulator/data/enrichment.txt
blobulator/data/enrichment_p.txt
blobulator/data/enrichment_s.txt
blobulator/data/ncprCMap.csv
blobulator/data/uverskyCMap.csv
blobulator-0.9.8.data/data/data/Table_S1.csv
blobulator-0.9.8.data/data/data/blobulated.csv
blobulator-0.9.8.data/data/data/disorderCMap.csv
blobulator-0.9.8.data/data/data/enrichCMap.csv
blobulator-0.9.8.data/data/data/enrichCMap_p.csv
blobulator-0.9.8.data/data/data/enrichCMap_s.csv
blobulator-0.9.8.data/data/data/enrichment.csv
blobulator-0.9.8.data/data/data/enrichment.txt
blobulator-0.9.8.data/data/data/enrichment_p.txt
blobulator-0.9.8.data/data/data/enrichment_s.txt
blobulator-0.9.8.data/data/data/ncprCMap.csv
blobulator-0.9.8.data/data/data/uverskyCMap.csv
blobulator-0.9.8.dist-info/licenses/LICENSE
blobulator-0.9.8.dist-info/METADATA
blobulator-0.9.8.dist-info/WHEEL
blobulator-0.9.8.dist-info/top_level.txt
blobulator-0.9.8.dist-info/RECORD
