Metadata-Version: 2.4
Name: blobulator
Version: 0.9.8
Summary: Edge Detection in Protein Sequences
Home-page: https://github.com/BranniganLab/blobulator
Author: Brannigan Lab
Author-email: Brannigan Lab <grace.brannigan@rutgers.edu>
Project-URL: Homepage, https://github.com/BranniganLab/blobulator
Project-URL: Issues, https://github.com/BranniganLab/blobulator/issues
Classifier: Intended Audience :: Science/Research
Classifier: Operating System :: POSIX :: Linux
Classifier: Programming Language :: Python :: 3.10
Classifier: License :: OSI Approved :: GNU General Public License v3 or later (GPLv3+)
Classifier: Operating System :: OS Independent
Requires-Python: >=3.10
License-File: LICENSE
Requires-Dist: Bio
Requires-Dist: numpy>=1.22.0
Requires-Dist: pandas>=1.4.0
Requires-Dist: matplotlib>=3.5.0
Requires-Dist: importlib_resources>=1.4
Requires-Dist: wtforms
Requires-Dist: flask
Requires-Dist: flask_restful
Requires-Dist: flask_cors
Requires-Dist: flask_session
Requires-Dist: svglib
Requires-Dist: reportlab
Dynamic: author
Dynamic: home-page
Dynamic: license-file
